{
  "$schema": "https://tree-sitter.github.io/tree-sitter/assets/schemas/grammar.schema.json",
  "name": "luna",
  "rules": {
    "source_file": {
      "type": "REPEAT",
      "content": {
        "type": "SYMBOL",
        "name": "module_statement"
      }
    },
    "module_statement": {
      "type": "SEQ",
      "members": [
        {
          "type": "SYMBOL",
          "name": "decl_statement"
        }
      ]
    },
    "function_statement": {
      "type": "SEQ",
      "members": [
        {
          "type": "CHOICE",
          "members": [
            {
              "type": "SYMBOL",
              "name": "decl_statement"
            },
            {
              "type": "SYMBOL",
              "name": "if_statement"
            },
            {
              "type": "SYMBOL",
              "name": "while_statement"
            },
            {
              "type": "SYMBOL",
              "name": "return_statement"
            },
            {
              "type": "SYMBOL",
              "name": "expression"
            }
          ]
        }
      ]
    },
    "if_statement": {
      "type": "SEQ",
      "members": [
        {
          "type": "STRING",
          "value": "if"
        },
        {
          "type": "SYMBOL",
          "name": "expression"
        },
        {
          "type": "SYMBOL",
          "name": "function_body"
        }
      ]
    },
    "while_statement": {
      "type": "SEQ",
      "members": [
        {
          "type": "STRING",
          "value": "while"
        },
        {
          "type": "SYMBOL",
          "name": "expression"
        },
        {
          "type": "SYMBOL",
          "name": "function_body"
        }
      ]
    },
    "return_statement": {
      "type": "SEQ",
      "members": [
        {
          "type": "STRING",
          "value": "return"
        },
        {
          "type": "SYMBOL",
          "name": "expression"
        }
      ]
    },
    "decl_statement": {
      "type": "SEQ",
      "members": [
        {
          "type": "CHOICE",
          "members": [
            {
              "type": "STRING",
              "value": "let"
            },
            {
              "type": "STRING",
              "value": "const"
            }
          ]
        },
        {
          "type": "SYMBOL",
          "name": "symbol"
        },
        {
          "type": "CHOICE",
          "members": [
            {
              "type": "SEQ",
              "members": [
                {
                  "type": "STRING",
                  "value": ":"
                },
                {
                  "type": "SYMBOL",
                  "name": "data_type"
                }
              ]
            },
            {
              "type": "BLANK"
            }
          ]
        },
        {
          "type": "STRING",
          "value": "="
        },
        {
          "type": "SYMBOL",
          "name": "expression"
        }
      ]
    },
    "data_type": {
      "type": "CHOICE",
      "members": [
        {
          "type": "SEQ",
          "members": [
            {
              "type": "STRING",
              "value": "*"
            },
            {
              "type": "SYMBOL",
              "name": "data_type"
            }
          ]
        },
        {
          "type": "SEQ",
          "members": [
            {
              "type": "STRING",
              "value": "["
            },
            {
              "type": "SYMBOL",
              "name": "data_type"
            },
            {
              "type": "STRING",
              "value": ";"
            },
            {
              "type": "SYMBOL",
              "name": "number"
            },
            {
              "type": "STRING",
              "value": "]"
            }
          ]
        },
        {
          "type": "SYMBOL",
          "name": "qualified_symbol"
        }
      ]
    },
    "expression": {
      "type": "CHOICE",
      "members": [
        {
          "type": "SYMBOL",
          "name": "leaf_expression"
        },
        {
          "type": "SYMBOL",
          "name": "unary_expression"
        },
        {
          "type": "SYMBOL",
          "name": "postfix_expression"
        },
        {
          "type": "SYMBOL",
          "name": "binary_expression"
        }
      ]
    },
    "leaf_expression": {
      "type": "CHOICE",
      "members": [
        {
          "type": "SYMBOL",
          "name": "qualified_symbol"
        },
        {
          "type": "SYMBOL",
          "name": "number"
        }
      ]
    },
    "unary_expression": {
      "type": "CHOICE",
      "members": [
        {
          "type": "SEQ",
          "members": [
            {
              "type": "STRING",
              "value": "("
            },
            {
              "type": "SYMBOL",
              "name": "expression"
            },
            {
              "type": "STRING",
              "value": ")"
            }
          ]
        },
        {
          "type": "SYMBOL",
          "name": "module_definition_expression"
        },
        {
          "type": "SYMBOL",
          "name": "function_definition_expression"
        },
        {
          "type": "SYMBOL",
          "name": "struct_definition_expression"
        },
        {
          "type": "SYMBOL",
          "name": "struct_initialization_expression"
        },
        {
          "type": "SYMBOL",
          "name": "enum_definition_expression"
        },
        {
          "type": "PREC_RIGHT",
          "value": 100,
          "content": {
            "type": "SEQ",
            "members": [
              {
                "type": "STRING",
                "value": "++"
              },
              {
                "type": "SYMBOL",
                "name": "expression"
              }
            ]
          }
        },
        {
          "type": "PREC_RIGHT",
          "value": 100,
          "content": {
            "type": "SEQ",
            "members": [
              {
                "type": "STRING",
                "value": "--"
              },
              {
                "type": "SYMBOL",
                "name": "expression"
              }
            ]
          }
        },
        {
          "type": "PREC_RIGHT",
          "value": 100,
          "content": {
            "type": "SEQ",
            "members": [
              {
                "type": "STRING",
                "value": "&"
              },
              {
                "type": "SYMBOL",
                "name": "expression"
              }
            ]
          }
        },
        {
          "type": "PREC_RIGHT",
          "value": 100,
          "content": {
            "type": "SEQ",
            "members": [
              {
                "type": "STRING",
                "value": "*"
              },
              {
                "type": "SYMBOL",
                "name": "expression"
              }
            ]
          }
        },
        {
          "type": "PREC_RIGHT",
          "value": 100,
          "content": {
            "type": "SEQ",
            "members": [
              {
                "type": "STRING",
                "value": "!"
              },
              {
                "type": "SYMBOL",
                "name": "expression"
              }
            ]
          }
        }
      ]
    },
    "postfix_expression": {
      "type": "CHOICE",
      "members": [
        {
          "type": "PREC_RIGHT",
          "value": 200,
          "content": {
            "type": "SEQ",
            "members": [
              {
                "type": "SYMBOL",
                "name": "expression"
              },
              {
                "type": "STRING",
                "value": "["
              },
              {
                "type": "SYMBOL",
                "name": "expression"
              },
              {
                "type": "STRING",
                "value": "]"
              }
            ]
          }
        },
        {
          "type": "PREC_LEFT",
          "value": 200,
          "content": {
            "type": "SEQ",
            "members": [
              {
                "type": "SYMBOL",
                "name": "expression"
              },
              {
                "type": "STRING",
                "value": "++"
              }
            ]
          }
        },
        {
          "type": "PREC_LEFT",
          "value": 200,
          "content": {
            "type": "SEQ",
            "members": [
              {
                "type": "SYMBOL",
                "name": "expression"
              },
              {
                "type": "STRING",
                "value": "--"
              }
            ]
          }
        },
        {
          "type": "PREC_LEFT",
          "value": 200,
          "content": {
            "type": "SEQ",
            "members": [
              {
                "type": "SYMBOL",
                "name": "qualified_symbol"
              },
              {
                "type": "STRING",
                "value": "("
              },
              {
                "type": "REPEAT",
                "content": {
                  "type": "SEQ",
                  "members": [
                    {
                      "type": "SYMBOL",
                      "name": "expression"
                    },
                    {
                      "type": "STRING",
                      "value": ")"
                    }
                  ]
                }
              },
              {
                "type": "STRING",
                "value": ")"
              }
            ]
          }
        }
      ]
    },
    "field_accessor_expression": {
      "type": "SEQ",
      "members": [
        {
          "type": "STRING",
          "value": "."
        },
        {
          "type": "SYMBOL",
          "name": "symbol"
        }
      ]
    },
    "binary_expression": {
      "type": "CHOICE",
      "members": [
        {
          "type": "PREC_LEFT",
          "value": 15,
          "content": {
            "type": "SEQ",
            "members": [
              {
                "type": "SYMBOL",
                "name": "qualified_symbol"
              },
              {
                "type": "REPEAT",
                "content": {
                  "type": "SYMBOL",
                  "name": "field_accessor_expression"
                }
              }
            ]
          }
        },
        {
          "type": "PREC_LEFT",
          "value": 14,
          "content": {
            "type": "SEQ",
            "members": [
              {
                "type": "SYMBOL",
                "name": "expression"
              },
              {
                "type": "STRING",
                "value": "*"
              },
              {
                "type": "SYMBOL",
                "name": "expression"
              }
            ]
          }
        },
        {
          "type": "PREC_LEFT",
          "value": 14,
          "content": {
            "type": "SEQ",
            "members": [
              {
                "type": "SYMBOL",
                "name": "expression"
              },
              {
                "type": "STRING",
                "value": "/"
              },
              {
                "type": "SYMBOL",
                "name": "expression"
              }
            ]
          }
        },
        {
          "type": "PREC_LEFT",
          "value": 13,
          "content": {
            "type": "SEQ",
            "members": [
              {
                "type": "SYMBOL",
                "name": "expression"
              },
              {
                "type": "STRING",
                "value": "+"
              },
              {
                "type": "SYMBOL",
                "name": "expression"
              }
            ]
          }
        },
        {
          "type": "PREC_LEFT",
          "value": 13,
          "content": {
            "type": "SEQ",
            "members": [
              {
                "type": "SYMBOL",
                "name": "expression"
              },
              {
                "type": "STRING",
                "value": "-"
              },
              {
                "type": "SYMBOL",
                "name": "expression"
              }
            ]
          }
        },
        {
          "type": "PREC_LEFT",
          "value": 12,
          "content": {
            "type": "SEQ",
            "members": [
              {
                "type": "SYMBOL",
                "name": "expression"
              },
              {
                "type": "STRING",
                "value": "<<"
              },
              {
                "type": "SYMBOL",
                "name": "expression"
              }
            ]
          }
        },
        {
          "type": "PREC_LEFT",
          "value": 12,
          "content": {
            "type": "SEQ",
            "members": [
              {
                "type": "SYMBOL",
                "name": "expression"
              },
              {
                "type": "STRING",
                "value": ">>"
              },
              {
                "type": "SYMBOL",
                "name": "expression"
              }
            ]
          }
        },
        {
          "type": "PREC_LEFT",
          "value": 11,
          "content": {
            "type": "SEQ",
            "members": [
              {
                "type": "SYMBOL",
                "name": "expression"
              },
              {
                "type": "STRING",
                "value": "<"
              },
              {
                "type": "SYMBOL",
                "name": "expression"
              }
            ]
          }
        },
        {
          "type": "PREC_LEFT",
          "value": 11,
          "content": {
            "type": "SEQ",
            "members": [
              {
                "type": "SYMBOL",
                "name": "expression"
              },
              {
                "type": "STRING",
                "value": ">"
              },
              {
                "type": "SYMBOL",
                "name": "expression"
              }
            ]
          }
        },
        {
          "type": "PREC_LEFT",
          "value": 11,
          "content": {
            "type": "SEQ",
            "members": [
              {
                "type": "SYMBOL",
                "name": "expression"
              },
              {
                "type": "STRING",
                "value": "<="
              },
              {
                "type": "SYMBOL",
                "name": "expression"
              }
            ]
          }
        },
        {
          "type": "PREC_LEFT",
          "value": 11,
          "content": {
            "type": "SEQ",
            "members": [
              {
                "type": "SYMBOL",
                "name": "expression"
              },
              {
                "type": "STRING",
                "value": ">="
              },
              {
                "type": "SYMBOL",
                "name": "expression"
              }
            ]
          }
        },
        {
          "type": "PREC_LEFT",
          "value": 10,
          "content": {
            "type": "SEQ",
            "members": [
              {
                "type": "SYMBOL",
                "name": "expression"
              },
              {
                "type": "STRING",
                "value": "=="
              },
              {
                "type": "SYMBOL",
                "name": "expression"
              }
            ]
          }
        },
        {
          "type": "PREC_LEFT",
          "value": 10,
          "content": {
            "type": "SEQ",
            "members": [
              {
                "type": "SYMBOL",
                "name": "expression"
              },
              {
                "type": "STRING",
                "value": "!="
              },
              {
                "type": "SYMBOL",
                "name": "expression"
              }
            ]
          }
        },
        {
          "type": "PREC_LEFT",
          "value": 9,
          "content": {
            "type": "SEQ",
            "members": [
              {
                "type": "SYMBOL",
                "name": "expression"
              },
              {
                "type": "STRING",
                "value": "&"
              },
              {
                "type": "SYMBOL",
                "name": "expression"
              }
            ]
          }
        },
        {
          "type": "PREC_LEFT",
          "value": 8,
          "content": {
            "type": "SEQ",
            "members": [
              {
                "type": "SYMBOL",
                "name": "expression"
              },
              {
                "type": "STRING",
                "value": "^"
              },
              {
                "type": "SYMBOL",
                "name": "expression"
              }
            ]
          }
        },
        {
          "type": "PREC_LEFT",
          "value": 7,
          "content": {
            "type": "SEQ",
            "members": [
              {
                "type": "SYMBOL",
                "name": "expression"
              },
              {
                "type": "STRING",
                "value": "|"
              },
              {
                "type": "SYMBOL",
                "name": "expression"
              }
            ]
          }
        },
        {
          "type": "PREC_LEFT",
          "value": 6,
          "content": {
            "type": "SEQ",
            "members": [
              {
                "type": "SYMBOL",
                "name": "expression"
              },
              {
                "type": "STRING",
                "value": "&&"
              },
              {
                "type": "SYMBOL",
                "name": "expression"
              }
            ]
          }
        },
        {
          "type": "PREC_LEFT",
          "value": 5,
          "content": {
            "type": "SEQ",
            "members": [
              {
                "type": "SYMBOL",
                "name": "expression"
              },
              {
                "type": "STRING",
                "value": "||"
              },
              {
                "type": "SYMBOL",
                "name": "expression"
              }
            ]
          }
        },
        {
          "type": "PREC_LEFT",
          "value": 2,
          "content": {
            "type": "SEQ",
            "members": [
              {
                "type": "SYMBOL",
                "name": "expression"
              },
              {
                "type": "STRING",
                "value": ","
              },
              {
                "type": "SYMBOL",
                "name": "expression"
              }
            ]
          }
        },
        {
          "type": "PREC_LEFT",
          "value": 1,
          "content": {
            "type": "SEQ",
            "members": [
              {
                "type": "SYMBOL",
                "name": "expression"
              },
              {
                "type": "STRING",
                "value": "="
              },
              {
                "type": "SYMBOL",
                "name": "expression"
              }
            ]
          }
        }
      ]
    },
    "struct_initialization_expression": {
      "type": "SEQ",
      "members": [
        {
          "type": "STRING",
          "value": "."
        },
        {
          "type": "SYMBOL",
          "name": "qualified_symbol"
        },
        {
          "type": "SYMBOL",
          "name": "struct_initialization_body"
        }
      ]
    },
    "struct_initialization_body": {
      "type": "SEQ",
      "members": [
        {
          "type": "STRING",
          "value": "{"
        },
        {
          "type": "CHOICE",
          "members": [
            {
              "type": "SEQ",
              "members": [
                {
                  "type": "SEQ",
                  "members": [
                    {
                      "type": "SYMBOL",
                      "name": "symbol"
                    },
                    {
                      "type": "STRING",
                      "value": ":"
                    },
                    {
                      "type": "SYMBOL",
                      "name": "expression"
                    }
                  ]
                },
                {
                  "type": "REPEAT",
                  "content": {
                    "type": "SEQ",
                    "members": [
                      {
                        "type": "STRING",
                        "value": ","
                      },
                      {
                        "type": "SYMBOL",
                        "name": "symbol"
                      },
                      {
                        "type": "STRING",
                        "value": ":"
                      },
                      {
                        "type": "SYMBOL",
                        "name": "expression"
                      }
                    ]
                  }
                }
              ]
            },
            {
              "type": "BLANK"
            }
          ]
        },
        {
          "type": "CHOICE",
          "members": [
            {
              "type": "STRING",
              "value": ","
            },
            {
              "type": "BLANK"
            }
          ]
        },
        {
          "type": "STRING",
          "value": "}"
        }
      ]
    },
    "enum_definition_expression": {
      "type": "SEQ",
      "members": [
        {
          "type": "STRING",
          "value": "enum"
        },
        {
          "type": "SYMBOL",
          "name": "enum_definition_body"
        }
      ]
    },
    "enum_definition_body": {
      "type": "SEQ",
      "members": [
        {
          "type": "STRING",
          "value": "{"
        },
        {
          "type": "CHOICE",
          "members": [
            {
              "type": "SEQ",
              "members": [
                {
                  "type": "SYMBOL",
                  "name": "symbol"
                },
                {
                  "type": "REPEAT",
                  "content": {
                    "type": "SEQ",
                    "members": [
                      {
                        "type": "STRING",
                        "value": ","
                      },
                      {
                        "type": "SYMBOL",
                        "name": "symbol"
                      }
                    ]
                  }
                }
              ]
            },
            {
              "type": "BLANK"
            }
          ]
        },
        {
          "type": "CHOICE",
          "members": [
            {
              "type": "STRING",
              "value": ","
            },
            {
              "type": "BLANK"
            }
          ]
        },
        {
          "type": "STRING",
          "value": "}"
        }
      ]
    },
    "struct_definition_expression": {
      "type": "SEQ",
      "members": [
        {
          "type": "CHOICE",
          "members": [
            {
              "type": "STRING",
              "value": "struct"
            },
            {
              "type": "STRING",
              "value": "union"
            }
          ]
        },
        {
          "type": "SYMBOL",
          "name": "struct_definition_body"
        }
      ]
    },
    "struct_definition_body": {
      "type": "SEQ",
      "members": [
        {
          "type": "STRING",
          "value": "{"
        },
        {
          "type": "CHOICE",
          "members": [
            {
              "type": "SYMBOL",
              "name": "struct_definition_argument_list"
            },
            {
              "type": "BLANK"
            }
          ]
        },
        {
          "type": "STRING",
          "value": "}"
        }
      ]
    },
    "struct_definition_argument_list_item": {
      "type": "SEQ",
      "members": [
        {
          "type": "SYMBOL",
          "name": "symbol"
        },
        {
          "type": "STRING",
          "value": ":"
        },
        {
          "type": "SYMBOL",
          "name": "data_type"
        }
      ]
    },
    "struct_definition_argument_list": {
      "type": "SEQ",
      "members": [
        {
          "type": "SYMBOL",
          "name": "struct_definition_argument_list_item"
        },
        {
          "type": "REPEAT",
          "content": {
            "type": "SEQ",
            "members": [
              {
                "type": "STRING",
                "value": ","
              },
              {
                "type": "SYMBOL",
                "name": "struct_definition_argument_list_item"
              }
            ]
          }
        },
        {
          "type": "CHOICE",
          "members": [
            {
              "type": "STRING",
              "value": ","
            },
            {
              "type": "BLANK"
            }
          ]
        }
      ]
    },
    "function_definition_expression": {
      "type": "PREC_LEFT",
      "value": 100,
      "content": {
        "type": "SEQ",
        "members": [
          {
            "type": "STRING",
            "value": "fn"
          },
          {
            "type": "CHOICE",
            "members": [
              {
                "type": "SYMBOL",
                "name": "function_macros"
              },
              {
                "type": "BLANK"
              }
            ]
          },
          {
            "type": "STRING",
            "value": "("
          },
          {
            "type": "CHOICE",
            "members": [
              {
                "type": "SYMBOL",
                "name": "function_definition_argument_list"
              },
              {
                "type": "BLANK"
              }
            ]
          },
          {
            "type": "STRING",
            "value": ")"
          },
          {
            "type": "CHOICE",
            "members": [
              {
                "type": "SEQ",
                "members": [
                  {
                    "type": "STRING",
                    "value": ":"
                  },
                  {
                    "type": "SYMBOL",
                    "name": "data_type"
                  }
                ]
              },
              {
                "type": "BLANK"
              }
            ]
          },
          {
            "type": "CHOICE",
            "members": [
              {
                "type": "SYMBOL",
                "name": "function_body"
              },
              {
                "type": "BLANK"
              }
            ]
          }
        ]
      }
    },
    "function_macros": {
      "type": "SEQ",
      "members": [
        {
          "type": "SYMBOL",
          "name": "function_macro"
        },
        {
          "type": "REPEAT",
          "content": {
            "type": "SYMBOL",
            "name": "function_macro"
          }
        }
      ]
    },
    "function_macro": {
      "type": "SEQ",
      "members": [
        {
          "type": "STRING",
          "value": "@"
        },
        {
          "type": "CHOICE",
          "members": [
            {
              "type": "SEQ",
              "members": [
                {
                  "type": "STRING",
                  "value": "extern"
                },
                {
                  "type": "STRING",
                  "value": "["
                },
                {
                  "type": "SYMBOL",
                  "name": "string_literal"
                },
                {
                  "type": "STRING",
                  "value": "]"
                }
              ]
            },
            {
              "type": "STRING",
              "value": "variadic"
            }
          ]
        }
      ]
    },
    "function_definition_argument_list_item": {
      "type": "SEQ",
      "members": [
        {
          "type": "SYMBOL",
          "name": "symbol"
        },
        {
          "type": "STRING",
          "value": ":"
        },
        {
          "type": "SYMBOL",
          "name": "data_type"
        }
      ]
    },
    "function_definition_argument_list": {
      "type": "SEQ",
      "members": [
        {
          "type": "SYMBOL",
          "name": "function_definition_argument_list_item"
        },
        {
          "type": "REPEAT",
          "content": {
            "type": "SEQ",
            "members": [
              {
                "type": "STRING",
                "value": ","
              },
              {
                "type": "SYMBOL",
                "name": "function_definition_argument_list_item"
              }
            ]
          }
        },
        {
          "type": "CHOICE",
          "members": [
            {
              "type": "STRING",
              "value": ","
            },
            {
              "type": "BLANK"
            }
          ]
        }
      ]
    },
    "module_definition_expression": {
      "type": "SEQ",
      "members": [
        {
          "type": "STRING",
          "value": "mod"
        },
        {
          "type": "SYMBOL",
          "name": "module_body"
        }
      ]
    },
    "function_body": {
      "type": "SEQ",
      "members": [
        {
          "type": "STRING",
          "value": "{"
        },
        {
          "type": "REPEAT",
          "content": {
            "type": "SYMBOL",
            "name": "function_statement"
          }
        },
        {
          "type": "STRING",
          "value": "}"
        }
      ]
    },
    "module_body": {
      "type": "SEQ",
      "members": [
        {
          "type": "STRING",
          "value": "{"
        },
        {
          "type": "REPEAT",
          "content": {
            "type": "SYMBOL",
            "name": "module_statement"
          }
        },
        {
          "type": "STRING",
          "value": "}"
        }
      ]
    },
    "qualified_symbol": {
      "type": "SEQ",
      "members": [
        {
          "type": "SYMBOL",
          "name": "symbol"
        },
        {
          "type": "REPEAT",
          "content": {
            "type": "SEQ",
            "members": [
              {
                "type": "STRING",
                "value": "::"
              },
              {
                "type": "SYMBOL",
                "name": "symbol"
              }
            ]
          }
        }
      ]
    },
    "symbol": {
      "type": "PATTERN",
      "value": "[a-zA-Z_][a-zA-Z0-9_]*"
    },
    "number": {
      "type": "PATTERN",
      "value": "\\d+"
    },
    "string_literal": {
      "type": "TOKEN",
      "content": {
        "type": "SEQ",
        "members": [
          {
            "type": "STRING",
            "value": "\""
          },
          {
            "type": "REPEAT",
            "content": {
              "type": "CHOICE",
              "members": [
                {
                  "type": "PATTERN",
                  "value": "[^\"\\\\\\n]"
                },
                {
                  "type": "PATTERN",
                  "value": "\\\\."
                }
              ]
            }
          },
          {
            "type": "STRING",
            "value": "\""
          }
        ]
      }
    },
    "single_line_comment": {
      "type": "SEQ",
      "members": [
        {
          "type": "STRING",
          "value": "//"
        },
        {
          "type": "PATTERN",
          "value": ".*"
        }
      ]
    },
    "multi_line_commment": {
      "type": "SEQ",
      "members": [
        {
          "type": "STRING",
          "value": "/*"
        },
        {
          "type": "PATTERN",
          "value": "[^*]*\\*+([^/*][^*]*\\*+)*"
        },
        {
          "type": "STRING",
          "value": "/"
        }
      ]
    }
  },
  "extras": [
    {
      "type": "SYMBOL",
      "name": "single_line_comment"
    },
    {
      "type": "SYMBOL",
      "name": "multi_line_commment"
    },
    {
      "type": "PATTERN",
      "value": "\\s"
    }
  ],
  "conflicts": [],
  "precedences": [],
  "externals": [],
  "inline": [],
  "supertypes": [],
  "reserved": {}
}